fastzip/__init__.py
fastzip/__main__.py
fastzip/_crc32_combine.py
fastzip/chooser.py
fastzip/read.py
fastzip/types.py
fastzip/util.py
fastzip/write.py
fastzip-0.5.0.dist-info/LICENSE
fastzip-0.5.0.dist-info/METADATA
fastzip-0.5.0.dist-info/WHEEL
fastzip-0.5.0.dist-info/top_level.txt
fastzip-0.5.0.dist-info/RECORD
