Metadata-Version: 2.1
Name: fastzip
Version: 0.5.0
Summary: Simple, quick zip file creation
Home-page: https://github.com/fastzip/fastzip/
Author: Tim Hatch
Author-email: tim@timhatch.com
License: MIT
Requires-Python: >=3.8
License-File: LICENSE
Requires-Dist: click (>=7.0)
Requires-Dist: keke (<0.2.0,>=0.1.1)
Provides-Extra: all
Requires-Dist: zstandard (>=0.10.0) ; extra == 'all'
Requires-Dist: pywildcard (>=1.0.10) ; extra == 'all'
